README.rst
setup.py
plex_missing_episodes/__init__.py
plex_missing_episodes/plex_missing_episodes.py
plex_missing_episodes.egg-info/PKG-INFO
plex_missing_episodes.egg-info/SOURCES.txt
plex_missing_episodes.egg-info/dependency_links.txt
plex_missing_episodes.egg-info/entry_points.txt
plex_missing_episodes.egg-info/requires.txt
plex_missing_episodes.egg-info/top_level.txt