Metadata-Version: 1.0
Name: plex-missing-episodes
Version: 0.1.1
Summary: Torrent RSS downloader
Home-page: https://github.com/spillevink/plex_missing_episodes
Author: Jakob Hedman
Author-email: jakob@hedman.email
License: GNU GPLv3
Platform: UNKNOWN
